src/__init__.py
src/main.py
src/api/__init__.py
src/api/fetch_times.py
src/ui/__init__.py
src/ui/config_dialog.py
src/ui/tray_operations.py
time_to_pray-0.1.1.dist-info/LICENSE
time_to_pray-0.1.1.dist-info/METADATA
time_to_pray-0.1.1.dist-info/WHEEL
time_to_pray-0.1.1.dist-info/entry_points.txt
time_to_pray-0.1.1.dist-info/top_level.txt
time_to_pray-0.1.1.dist-info/RECORD
