Metadata-Version: 2.1
Name: time-to-pray
Version: 0.1.1
Summary: A desktop utility for Islamic prayer times
Home-page: https://github.com/omerbustun/time-to-pray
Author: Ömer Üstün
Author-email: omerbustun@gmail.com
Classifier: Programming Language :: Python :: 3
Classifier: License :: OSI Approved :: GNU General Public License v3 (GPLv3)
Classifier: Operating System :: OS Independent
Requires-Python: >=3.6
License-File: LICENSE
Requires-Dist: PyQt6
Requires-Dist: PyQt6 ==6.5.2
Requires-Dist: PyQt6-sip ==13.5.2
Requires-Dist: Requests ==2.31.0
